{"explain_about.md":"2740bcc7","explain_details.md":"36ea32cd","explain_index.md":"f6a66be8","explain_sponsor.md":"dbde468a","index.md":"3cb118ae","options_custom.md":"93a8f5d9","options_footer.md":"c67db39c","options_home.md":"37bd5750","options_index.md":"6e7bf070","options_nav.md":"3c7bd9b9","options_other.md":"705685a2","options_post.md":"c04dc617","template_friends.md":"96f4ed4a","template_index.md":"d251ee6f","template_login.md":"46b78276","widgets_index.md":"a7bf68d5","widgets_special-note.md":"efbe0231"}
